congo/__init__.py
congo/conf.py
congo/urls.py
congo/accounts/__init__.py
congo/accounts/admin.py
congo/accounts/backends.py
congo/accounts/forms.py
congo/accounts/models.py
congo/admin/__init__.py
congo/admin/actions.py
congo/admin/admin.py
congo/admin/dashboard.py
congo/admin/filters.py
congo/admin/menu.py
congo/cache/__init__.py
congo/cache/utils.py
congo/communication/__init__.py
congo/communication/admin.py
congo/communication/admin_forms.py
congo/communication/admin_views.py
congo/communication/classes.py
congo/communication/filters.py
congo/communication/models.py
congo/communication/views.py
congo/communication/backends/__init__.py
congo/communication/backends/base.py
congo/communication/backends/console.py
congo/communication/backends/filebased.py
congo/communication/backends/sendmail.py
congo/communication/backends/smsapi.py
congo/gallery/__init__.py
congo/gallery/admin.py
congo/gallery/classes.py
congo/gallery/mixins.py
congo/gallery/models.py
congo/locale/en/LC_MESSAGES/django.po
congo/locale/pl/LC_MESSAGES/django.po
congo/maintenance/__init__.py
congo/maintenance/admin.py
congo/maintenance/admin_views.py
congo/maintenance/filters.py
congo/maintenance/managers.py
congo/maintenance/middleware.py
congo/maintenance/models.py
congo/maintenance/views.py
congo/maintenance/audits/__init__.py
congo/maintenance/audits/test.py
congo/maintenance/audits/unused_user_accounts.py
congo/maintenance/jobs/__init__.py
congo/maintenance/jobs/clear_logs.py
congo/maintenance/jobs/clear_session.py
congo/maintenance/jobs/send_email_queue.py
congo/maintenance/jobs/send_sms_queue.py
congo/maintenance/jobs/test.py
congo/maintenance/logs/__init__.py
congo/maintenance/logs/filters.py
congo/maintenance/logs/handlers.py
congo/management/__init__.py
congo/management/commands/__init__.py
congo/management/commands/audit.py
congo/management/commands/cron.py
congo/management/commands/get_country_languages.py
congo/management/commands/parler2po.py
congo/management/commands/po2parler.py
django_congo3-3.2.1.dist-info/LICENSE
django_congo3-3.2.1.dist-info/METADATA
django_congo3-3.2.1.dist-info/WHEEL
django_congo3-3.2.1.dist-info/top_level.txt
django_congo3-3.2.1.dist-info/RECORD
