Metadata-Version: 2.1
Name: django-congo3
Version: 3.2.1
Summary: Congo 3 contains many useful tools for faster and more efficient Django application developing.
Home-page: https://integree.eu/en/solutions/congo/
Author: Integree Bussines Solutions
License: UNKNOWN
Download-URL: https://pypi.python.org/packages/source/d/django-congo/django-congo-3.2.1.zip
Platform: UNKNOWN
Classifier: Development Status :: 5 - Production/Stable
Classifier: Intended Audience :: Developers
Classifier: Operating System :: OS Independent
Classifier: Environment :: Web Environment
Classifier: Programming Language :: Python :: 3.6
Classifier: Framework :: Django :: 2.0
Classifier: License :: OSI Approved :: MIT License
Requires-Dist: django-admin-tools (~=0.8.0)
Requires-Dist: django-appconf (~=1.0.0)
Requires-Dist: django-bower (~=5.2.0)
Requires-Dist: django-filter (~=2.1.0)
Requires-Dist: django-mptt (~=0.9.0)
Requires-Dist: django-parler (~=1.9.0)
Requires-Dist: martor (~=1.2.0)
Requires-Dist: pillow (~=5.2.0)
Requires-Dist: premailer (~=3.1.0)
Requires-Dist: py-moneyed (~=0.8.0)
Requires-Dist: pycryptodome (~=3.6.0)
Requires-Dist: suds-jurko (~=0.6.0)
Requires-Dist: unidecode (~=1.0.0)
